csvy/__init__.py
csvy/readers.py
csvy/writers.py
pycsvy-0.2.2.dist-info/LICENSE
pycsvy-0.2.2.dist-info/METADATA
pycsvy-0.2.2.dist-info/WHEEL
pycsvy-0.2.2.dist-info/RECORD
