Metadata-Version: 2.1
Name: pycsvy
Version: 0.2.2
Summary: Python reader/writer for CSV files with YAML header information.
Home-page: https://github.com/ImperialCollegeLondon/pycsvy
License: BSD-3-Clause
Author: Diego Alonso Álvarez
Author-email: d.alonso-alvarez@imperial.ac.uk
Requires-Python: >=3.8,<4.0
Classifier: Development Status :: 4 - Beta
Classifier: Intended Audience :: Developers
Classifier: Intended Audience :: Science/Research
Classifier: License :: OSI Approved :: BSD License
Classifier: Programming Language :: Python :: 3
Classifier: Programming Language :: Python :: 3.8
Classifier: Programming Language :: Python :: 3.9
Classifier: Programming Language :: Python :: 3.10
Classifier: Programming Language :: Python :: 3.11
Classifier: Programming Language :: Python :: 3
Classifier: Programming Language :: Python :: 3.10
Classifier: Programming Language :: Python :: 3.11
Classifier: Programming Language :: Python :: 3.8
Classifier: Programming Language :: Python :: 3.9
Requires-Dist: PyYAML (>=6.0,<7.0)
Project-URL: Repository, https://github.com/ImperialCollegeLondon/pycsvy
